fifolock.py
fifolock-0.0.20.dist-info/LICENSE
fifolock-0.0.20.dist-info/METADATA
fifolock-0.0.20.dist-info/WHEEL
fifolock-0.0.20.dist-info/top_level.txt
fifolock-0.0.20.dist-info/RECORD
